fluent_discourse/__init__.py
fluent_discourse/discourse.py
fluent_discourse/errors.py
fluent_discourse-1.0.1.dist-info/LICENSE
fluent_discourse-1.0.1.dist-info/METADATA
fluent_discourse-1.0.1.dist-info/WHEEL
fluent_discourse-1.0.1.dist-info/top_level.txt
fluent_discourse-1.0.1.dist-info/RECORD
