Metadata-Version: 2.1
Name: fluent-discourse
Version: 1.0.1
Summary: A fluent interface to the Discourse API
Home-page: https://github.com/graydenshand/fluent_discourse
Author: Grayden Shand
Author-email: graydenshand@gmail.com
Project-URL: Bug Tracker, https://github.com/graydenshand/fluent_discourse/issues
Classifier: Programming Language :: Python :: 3
Classifier: License :: OSI Approved :: MIT License
Classifier: Operating System :: OS Independent
Requires-Python: >=3.6
License-File: LICENSE
Requires-Dist: requests
